normflowpy/__init__.py
normflowpy/base_flow.py
normflowpy/nf_model.py
normflowpy/variational_dequantization_flow_model.py
normflowpy/base_nets/__init__.py
normflowpy/base_nets/made.py
normflowpy/base_nets/mlp_base_net.py
normflowpy/base_nets/real_nvp_conv_base.py
normflowpy/flows/__init__.py
normflowpy/flows/act_norm.py
normflowpy/flows/affine.py
normflowpy/flows/iaf.py
normflowpy/flows/invertible_one_on_one.py
normflowpy/flows/maf.py
normflowpy/flows/squeeze.py
normflowpy/flows/vector2tensor.py
normflowpy/flows/flow_modules/__init__.py
normflowpy/flows/flow_modules/batch_normalization.py
normflowpy/flows/flow_modules/sigmoid.py
normflowpy/flows/helpers/__init__.py
normflowpy/flows/helpers/logistic.py
normflowpy/flows/helpers/safe_log.py
normflowpy/flows/splines/__init__.py
normflowpy/flows/splines/cubic_spline_flow.py
normflowpy/flows/splines/cubic_spline_function.py
normflowpy/flows/splines/pspline_flows.py
normflowpy/flows/splines/spline_flows.py
normflowpy/flows/splines/utils.py
normflowpy/preprocess/__init__.py
normflowpy/preprocess/dequantized.py
normflowpy/preprocess/input_padding.py
normflowpy/preprocess/numpy2tensor.py
normflowpy/priors/__init__.py
normflowpy/priors/trainable_prior.py
normflowpy-0.2.0.dist-info/LICENSE
normflowpy-0.2.0.dist-info/METADATA
normflowpy-0.2.0.dist-info/WHEEL
normflowpy-0.2.0.dist-info/top_level.txt
normflowpy-0.2.0.dist-info/RECORD
