Metadata-Version: 2.1
Name: normflowpy
Version: 0.2.0
Summary: A Normalizing flow package using PyTorch
Home-page: UNKNOWN
License: UNKNOWN
Platform: UNKNOWN
Classifier: Programming Language :: Python :: 3
Classifier: License :: OSI Approved :: MIT License
Classifier: Operating System :: OS Independent
Classifier: Topic :: Scientific/Engineering :: Artificial Intelligence
Requires-Python: >=3.6
Requires-Dist: torch
Requires-Dist: numpy
